ebook_homebrew/__init__.py
ebook_homebrew/archive.py
ebook_homebrew/cli.py
ebook_homebrew/convert.py
ebook_homebrew/core.py
ebook_homebrew/exceptions.py
ebook_homebrew/helper.py
ebook_homebrew/rdb.py
ebook_homebrew/rename.py
ebook_homebrew/rest.py
ebook_homebrew/models/__init__.py
ebook_homebrew/models/rest_models.py
ebook_homebrew/models/uploaded_files_models.py
ebook_homebrew/static/index.html
ebook_homebrew/utils/__init__.py
ebook_homebrew/utils/logging.py
ebook_homebrew/utils/logging.yaml
ebook_homebrew-2.1.4.dist-info/LICENSE
ebook_homebrew-2.1.4.dist-info/METADATA
ebook_homebrew-2.1.4.dist-info/WHEEL
ebook_homebrew-2.1.4.dist-info/entry_points.txt
ebook_homebrew-2.1.4.dist-info/top_level.txt
ebook_homebrew-2.1.4.dist-info/RECORD
