Metadata-Version: 2.1
Name: ebook-homebrew
Version: 2.1.4
Summary: Rename image file to only digit name and convert ebook files.
Home-page: https://github.com/tubone24/ebook_homebrew
Author: tubone24
Author-email: tubo.yyyuuu@gmail.com
License: MIT
Project-URL: ProjectBlog, https://blog.tubone-project24.xyz
Project-URL: Documentation, https://ebook-homebrew.readthedocs.io/en/latest/
Keywords: ebook,rename,pdf,rest
Platform: any
Classifier: Development Status :: 5 - Production/Stable
Classifier: Intended Audience :: Developers
Classifier: License :: OSI Approved :: MIT License
Classifier: Operating System :: OS Independent
Classifier: Topic :: Documentation :: Sphinx
Classifier: Programming Language :: Python
Classifier: Programming Language :: Python :: 3.6
Classifier: Programming Language :: Python :: 3.7
Classifier: Topic :: Software Development :: Libraries :: Python Modules
Classifier: Topic :: Internet :: WWW/HTTP :: Browsers
Requires-Python: >= 3.6
Requires-Dist: Pillow (>=5.3.0)
Requires-Dist: PyPDF2 (==1.26.0)
Requires-Dist: PyYAML (>=4.2b1)
Requires-Dist: responder (==1.3.2)
Requires-Dist: marshmallow (==2.19.5)
Requires-Dist: SQLAlchemy (==1.3.8)
Requires-Dist: six (==1.12)
Requires-Dist: uvloop (==0.12.*) ; sys_platform != "win32" and sys_platform != "cygwin" and sys_platform != "cli"
Provides-Extra: develop
Requires-Dist: black (==19.3b0) ; extra == 'develop'
Requires-Dist: pytest (==4.5.0) ; extra == 'develop'
Requires-Dist: pytest-cov (==2.7.1) ; extra == 'develop'
Requires-Dist: pytest-pythonpath (==0.7.3) ; extra == 'develop'
Requires-Dist: flake8 (==3.7.7) ; extra == 'develop'
Requires-Dist: pep8 (==1.7.1) ; extra == 'develop'
Requires-Dist: pyflakes (==2.1.1) ; extra == 'develop'
Requires-Dist: pytest-flake8 (==1.0.4) ; extra == 'develop'
Requires-Dist: pytest-pep8 (==1.0.6) ; extra == 'develop'
Requires-Dist: coverage (==4.5.4) ; extra == 'develop'
Requires-Dist: codecov (==2.0.15) ; extra == 'develop'
Provides-Extra: docs
Requires-Dist: Sphinx (==2.2.0) ; extra == 'docs'
Requires-Dist: sphinx-rtd-theme (==0.4.3) ; extra == 'docs'
Requires-Dist: sphinxcontrib-openapi (==0.5.0) ; extra == 'docs'
Requires-Dist: sphinxcontrib-websupport (==1.1.2) ; extra == 'docs'
